{
  "equity": 93365.33,
  "initial_equity": 100000.0,
  "last_equity": 94186.11,
  "returns": {
    "total_return_%": -6.634669999999998,
    "return_1d_%": 0.0,
    "return_1w_%": -1.1116885856929493,
    "return_1m_%": -7.560424615602123
  },
  "positions": [
    {
      "symbol": "BTCUSD",
      "qty": 0.850795007,
      "market_value": 93705.796355,
      "unrealized_pl": -808.870812,
      "unrealized_plpc": -0.0085581511975362
    }
  ],
  "last_updated": "2025-11-01T07:13:31.374095+00:00"
}