{
  "equity": 99332.47,
  "initial_equity": 100000.0,
  "last_equity": 97838.73,
  "returns": {
    "total_return_%": -0.667529999999994,
    "return_1d_%": 0.0,
    "return_1w_%": 2.371817604402371,
    "return_1m_%": -0.19873351092085656
  },
  "positions": [
    {
      "symbol": "BTCUSD",
      "qty": 0.850795007,
      "market_value": 99359.258561,
      "unrealized_pl": 4844.591394,
      "unrealized_plpc": 0.0512575618072059
    }
  ],
  "last_updated": "2025-09-18T02:54:10.973283+00:00"
}